Metadata-Version: 1.1
Name: ciavelli
Version: 0.9
Summary: A CMake based package manager for C++
Home-page: https://github.com/ShadowItaly/Ciavelli
Author: Alexander Leonhardt
Author-email: equinox.salexander@gmail.com
License: MIT
Download-URL: https://github.com/ShadowItaly/Ciavelli/archive/version0.1.tar.gz
Keywords: CMake,Package manager,C++
Platform: UNKNOWN
Classifier: Development Status :: 3 - Alpha
Classifier: Intended Audience :: Developers
Classifier: Topic :: Software Development :: Build Tools
Classifier: License :: OSI Approved :: MIT License
Classifier: Programming Language :: Python :: 3
Classifier: Programming Language :: Python :: 3.4
Classifier: Programming Language :: Python :: 3.5
Classifier: Programming Language :: Python :: 3.6
